Metadata-Version: 2.1
Name: nr.git-subrepo
Version: 1.0.1
Summary: Create working trees of other Git repositories and track them in your parent repository.
Home-page: https://git.niklasrosenstein.com/NiklasRosenstein/git-subrepo
Author: Niklas Rosenstein
Author-email: rosensteinniklas@gmail.com
License: MIT
Platform: UNKNOWN
